{
	"backtrace" : 0,
	"backtraceGraph" : 
	{
		"commands" : [],
		"files" : 
		[
			"capture/CMakeLists.txt"
		],
		"nodes" : 
		[
			{
				"file" : 0
			}
		]
	},
	"id" : "capture_autogen::@47b030bd5dc7e8704d57",
	"isGeneratorProvided" : true,
	"name" : "capture_autogen",
	"paths" : 
	{
		"build" : "capture",
		"source" : "capture"
	},
	"sourceGroups" : 
	[
		{
			"name" : "",
			"sourceIndexes" : 
			[
				0
			]
		},
		{
			"name" : "CMake Rules",
			"sourceIndexes" : 
			[
				1
			]
		}
	],
	"sources" : 
	[
		{
			"backtrace" : 0,
			"isGenerated" : true,
			"path" : "build/atk_dlrv1126-Debug/capture/CMakeFiles/capture_autogen",
			"sourceGroupIndex" : 0
		},
		{
			"backtrace" : 0,
			"isGenerated" : true,
			"path" : "build/atk_dlrv1126-Debug/capture/CMakeFiles/capture_autogen.rule",
			"sourceGroupIndex" : 1
		}
	],
	"type" : "UTILITY"
}
